preliz/__init__.py
preliz/distributions/__init__.py
preliz/distributions/asymmetric_laplace.py
preliz/distributions/bernoulli.py
preliz/distributions/beta.py
preliz/distributions/betabinomial.py
preliz/distributions/betascaled.py
preliz/distributions/binomial.py
preliz/distributions/categorical.py
preliz/distributions/cauchy.py
preliz/distributions/censored.py
preliz/distributions/chi_squared.py
preliz/distributions/continuous_multivariate.py
preliz/distributions/discrete_uniform.py
preliz/distributions/discrete_weibull.py
preliz/distributions/distributions.py
preliz/distributions/distributions_multivariate.py
preliz/distributions/exgaussian.py
preliz/distributions/exponential.py
preliz/distributions/gamma.py
preliz/distributions/geometric.py
preliz/distributions/gumbel.py
preliz/distributions/halfcauchy.py
preliz/distributions/halfnormal.py
preliz/distributions/halfstudentt.py
preliz/distributions/hurdle.py
preliz/distributions/hypergeometric.py
preliz/distributions/inversegamma.py
preliz/distributions/kumaraswamy.py
preliz/distributions/laplace.py
preliz/distributions/logistic.py
preliz/distributions/logitnormal.py
preliz/distributions/loglogistic.py
preliz/distributions/lognormal.py
preliz/distributions/mixture.py
preliz/distributions/moyal.py
preliz/distributions/negativebinomial.py
preliz/distributions/normal.py
preliz/distributions/pareto.py
preliz/distributions/plot.py
preliz/distributions/poisson.py
preliz/distributions/rice.py
preliz/distributions/scaled_inverse_chi_squared.py
preliz/distributions/skew_studentt.py
preliz/distributions/skewnormal.py
preliz/distributions/studentt.py
preliz/distributions/triangular.py
preliz/distributions/truncated.py
preliz/distributions/truncatednormal.py
preliz/distributions/uniform.py
preliz/distributions/vonmises.py
preliz/distributions/wald.py
preliz/distributions/weibull.py
preliz/distributions/zi_binomial.py
preliz/distributions/zi_negativebinomial.py
preliz/distributions/zi_poisson.py
preliz/internal/__init__.py
preliz-0.23.0.dist-info/licenses/LICENSE
preliz-0.23.0.dist-info/WHEEL
preliz-0.23.0.dist-info/METADATA
preliz-0.23.0.dist-info/RECORD
