Metadata-Version: 2.4
Name: preliz
Version: 0.23.0
Summary: Exploring and eliciting probability distributions.
Author-email: ArviZ team <arviz.devs@gmail.com>
Requires-Python: >=3.11
Classifier: Development Status :: 3 - Alpha
Classifier: Intended Audience :: Science/Research
Classifier: Intended Audience :: Education
Classifier: License :: OSI Approved :: Apache Software License
Classifier: Operating System :: OS Independent
Classifier: Programming Language :: Python
Classifier: Programming Language :: Python :: 3
Classifier: Programming Language :: Python :: 3.11
Classifier: Programming Language :: Python :: 3.12
Classifier: Programming Language :: Python :: 3.13
License-File: LICENSE
Requires-Dist: arviz_stats>=0.6.0
Requires-Dist: matplotlib>=3.9
Requires-Dist: numba>=0.62
Requires-Dist: numpy>=2.0
Requires-Dist: scipy>=1.12
Requires-Dist: nbclient>=0.2 ; extra == "full"
Requires-Dist: ipywidgets ; extra == "full"
Requires-Dist: ipympl ; extra == "full"
Requires-Dist: jupyterlab ; extra == "lab"
Requires-Dist: notebook ; extra == "notebook"
Project-URL: documentation, https://preliz.readthedocs.io
Project-URL: funding, https://opencollective.com/arviz
Project-URL: source, https://github.com/arviz-devs/preliz
Project-URL: tracker, https://github.com/arviz-devs/preliz/issues
Provides-Extra: full
Provides-Extra: lab
Provides-Extra: notebook
